jtheta/__init__.py
jtheta/client.py
jtheta/config.py
jtheta/test_validate.py
jtheta-0.1.1.dist-info/licenses/LICENSE
jtheta-0.1.1.dist-info/METADATA
jtheta-0.1.1.dist-info/WHEEL
jtheta-0.1.1.dist-info/top_level.txt
jtheta-0.1.1.dist-info/RECORD
