Metadata-Version: 2.4
Name: jtheta
Version: 0.1.1
Summary: SDK for interacting with the jtheta.ai API
Author-email: JTheta Team <jtheta.ai@gmail.com>
License: MIT
Classifier: Programming Language :: Python :: 3
Classifier: License :: OSI Approved :: MIT License
Classifier: Operating System :: OS Independent
Requires-Python: <3.14,>=3.8
License-File: LICENSE
Requires-Dist: requests
Dynamic: license-file
